execution_timer/__init__.py
execution_timer/execution_timer.py
timer_decorator-0.1.3.dist-info/LICENSE
timer_decorator-0.1.3.dist-info/METADATA
timer_decorator-0.1.3.dist-info/WHEEL
timer_decorator-0.1.3.dist-info/top_level.txt
timer_decorator-0.1.3.dist-info/RECORD
